readwise_to_apple_notes/__init__.py
readwise_to_apple_notes/__main__.py
readwise_to_apple_notes/cli.py
readwise_to_apple_notes/utils.py
readwise_to_apple_notes-0.1.0.dist-info/LICENSE
readwise_to_apple_notes-0.1.0.dist-info/METADATA
readwise_to_apple_notes-0.1.0.dist-info/WHEEL
readwise_to_apple_notes-0.1.0.dist-info/entry_points.txt
readwise_to_apple_notes-0.1.0.dist-info/RECORD
