Metadata-Version: 2.1
Name: readwise-to-apple-notes
Version: 0.1.0
Summary: Export Readwise highlights to Apple Notes.
License: Apache-2.0
Author: Scott Carvalho
Author-email: scottcarvalho71@gmail.com
Requires-Python: >=3.12,<4.0
Classifier: License :: OSI Approved :: Apache Software License
Classifier: Programming Language :: Python :: 3
Classifier: Programming Language :: Python :: 3.12
Requires-Dist: click (>=8.1.7,<9.0.0)
Requires-Dist: python-dotenv (>=1.0.1,<2.0.0)
Requires-Dist: readwise (>=1.1.0,<2.0.0)
Project-URL: Changelog, https://github.com/Scarvy/readwise-to-apple-notes/releases
Project-URL: CI, https://github.com/Scarvy/readwise-to-apple-notes/actions
Project-URL: Homepage, https://github.com/Scarvy/readwise-to-apple-notes
Project-URL: Issues, https://github.com/Scarvy/readwise-to-apple-notes/issues
